dstr/__init__.py
dstr/_modidx.py
dstr/char.py
dstr/core.py
dstr/enum.py
dstr/meta.py
dstr/name.py
dstr/size.py
dstr/strs.py
dstr/type.py
dstr/util.py
dstr-0.0.1.dist-info/LICENSE
dstr-0.0.1.dist-info/METADATA
dstr-0.0.1.dist-info/WHEEL
dstr-0.0.1.dist-info/entry_points.txt
dstr-0.0.1.dist-info/top_level.txt
dstr-0.0.1.dist-info/RECORD
