Metadata-Version: 2.1
Name: dstr
Version: 0.0.1
Summary: dim string
Home-page: https://github.com/dsm-72/dstr
Author: dsm-72
Author-email: sumner.magruder@yale.edu
License: Apache Software License 2.0
Keywords: dim dims ndim dstr str dimmed numpy array python py torch pytorch lightning pl trc enum
Classifier: Development Status :: 4 - Beta
Classifier: Intended Audience :: Developers
Classifier: Natural Language :: English
Classifier: Programming Language :: Python :: 3.11
Classifier: License :: OSI Approved :: Apache Software License
Requires-Python: >=3.11
License-File: LICENSE
Requires-Dist: nchr
Requires-Dist: nlit
Requires-Dist: atup
Provides-Extra: dev
Requires-Dist: numpy ; extra == 'dev'
Requires-Dist: pandas ; extra == 'dev'
Requires-Dist: matplotlib ; extra == 'dev'
Requires-Dist: torch ; extra == 'dev'
Requires-Dist: pytorch-lightning ; extra == 'dev'
Requires-Dist: torchvision ; extra == 'dev'
